.VERSION
AUTHORS.rst
CONTRIBUTING.rst
HISTORY.rst
LICENSE
MANIFEST.in
Pipfile
Pipfile.lock
README.rst
USAGE.rst
dev-requirements.txt
requirements.txt
setup.cfg
setup.py
awsenergylabelerlib/.VERSION
awsenergylabelerlib/AUTHORS.rst
awsenergylabelerlib/CONTRIBUTING.rst
awsenergylabelerlib/HISTORY.rst
awsenergylabelerlib/LICENSE
awsenergylabelerlib/Pipfile
awsenergylabelerlib/Pipfile.lock
awsenergylabelerlib/README.rst
awsenergylabelerlib/USAGE.rst
awsenergylabelerlib/__init__.py
awsenergylabelerlib/_version.py
awsenergylabelerlib/awsenergylabelerlib.py
awsenergylabelerlib/awsenergylabelerlibexceptions.py
awsenergylabelerlib/configuration.py
awsenergylabelerlib/datamodels.py
awsenergylabelerlib/dev-requirements.txt
awsenergylabelerlib/entities.py
awsenergylabelerlib/labels.py
awsenergylabelerlib/requirements.txt
awsenergylabelerlib/schemas.py
awsenergylabelerlib/validations.py
awsenergylabelerlib.egg-info/PKG-INFO
awsenergylabelerlib.egg-info/SOURCES.txt
awsenergylabelerlib.egg-info/dependency_links.txt
awsenergylabelerlib.egg-info/not-zip-safe
awsenergylabelerlib.egg-info/requires.txt
awsenergylabelerlib.egg-info/top_level.txt
docs/Makefile
docs/authors.rst
docs/conf.py
docs/contributing.rst
docs/history.rst
docs/index.rst
docs/installation.rst
docs/readme.rst
docs/usage.rst
tests/test_awsenergylabelerlib.py
tests/test_entities.py
tests/test_validations.py