Metadata-Version: 2.1
Name: awsenergylabelerlib
Version: 3.2.1
Summary: Project energy labeling accounts and landing zone based on findings of Security Hub in AWS cloud.
Home-page: https://github.com/schubergphilis/awsenergylabelerlib.git
Author: Costas Tyfoxylos
Author-email: ctyfoxylos@schubergphilis.com
License: MIT
Keywords: awsenergylabelerlib energy labeling aws security hub landing zone
Classifier: Development Status :: 4 - Beta
Classifier: Intended Audience :: Developers
Classifier: License :: OSI Approved :: MIT License
Classifier: Natural Language :: English
Classifier: Programming Language :: Python :: 3.7
License-File: LICENSE
License-File: AUTHORS.rst
